groupmaker/__init__.py
groupmaker/counting.py
groupmaker/file_io.py
groupmaker/generation.py
groupmaker/pairing.py
groupmaker/scoring.py
groupmaker/solver.py
groupmaker/table.py
groupmaker-0.2.1.dist-info/DESCRIPTION.rst
groupmaker-0.2.1.dist-info/METADATA
groupmaker-0.2.1.dist-info/RECORD
groupmaker-0.2.1.dist-info/WHEEL
groupmaker-0.2.1.dist-info/entry_points.txt
groupmaker-0.2.1.dist-info/metadata.json
groupmaker-0.2.1.dist-info/top_level.txt
groupmaker-0.2.1.dist-info/zip-safe
