Metadata-Version: 2.0
Name: groupmaker
Version: 0.2.1
Summary: Command line tool for making classroom groups.
Home-page: https://github.com/selassid/groupmaker
Author: David Selassie
Author-email: selassid@gmail.com
License: BSD
Platform: UNKNOWN
Requires-Dist: tabulate
